00-01-10-counter-circuit/5_36.v
//Jason Hatfield - # 29163434
//CSE 241 HW8, problem 5.36, to submit .v, .vvp, _wv.vcd. screenshot, script


// Module for T-Flip Flop

module tff(q, t, clk, reset);

   output q;
   reg q;
   input t, clk, reset;

   always @ ( posedge clk, negedge reset )
	if (~reset) 
	   begin
		q <= 1'b0;
	   end
	
	else if (t)
	   begin
		q <= !q;
           end

endmodule

//End of TFF module

//Begin Circuit Module

module counter(a, b, clk, reset);

   output a, b;

   input clk, reset;

   wire ta, tb;

   assign ta = a | b;
   assign tb =  ~a | b;

   tff t1(a, ta, clk, reset);
   tff t2(b, tb, clk, reset);

endmodule

//End of Circuit module

00-01-10-counter-circuit/5_36_tb.v
//Jason Hatfield - #29163434
//HW8 Test bench for 00-01-10-counter circuit

module counter_tb;

   reg clk, reset;

   wire ta, tb;

   counter c1(ta, tb, clk, reset);

   initial #200 $finish;

   initial
	
	begin
	
	   reset = 0;
	   clk = 0;

	   #5 reset = 1;

	   repeat(16)
		
		#5 clk = ~clk;

   	end

   initial 
   	
	begin

	   $monitor("time = %g clk = %b reset = %b a_out = %b b_out = %b", $time, clk, reset, ta, tb);
	   $dumpfile("5_36_wv.vcd");
	   $dumpvars;

   	end

endmodule

hw8/5_36_wv.vcd
$date
	Mon Nov 25 13:20:22 2013
$end
$version
	Icarus Verilog
$end
$timescale
	1s
$end
$scope module counter_tb $end
$var wire 1 ! ta $end
$var wire 1 " tb $end
$var reg 1 # clk $end
$var reg 1 $ reset $end
$scope module c1 $end
$var wire 1 ! a $end
$var wire 1 " b $end
$var wire 1 % clk $end
$var wire 1 & reset $end
$var wire 1 ' ta $end
$var wire 1 ( tb $end
$scope module t1 $end
$var wire 1 % clk $end
$var wire 1 & reset $end
$var wire 1 ' t $end
$var reg 1 ) q $end
$upscope $end
$scope module t2 $end
$var wire 1 % clk $end
$var wire 1 & reset $end
$var wire 1 ( t $end
$var reg 1 * q $end
$upscope $end
$upscope $end
$upscope $end
$enddefinitions $end
#0
$dumpvars
0*
0)
1(
0'
0&
0%
0$
0#
0"
0!
$end
#5
1$
1&
#10
1'
1*
1"
1#
1%
#15
0#
0%
#20
0(
1)
1!
0*
0"
1#
1%
#25
0#
0%
#30
1(
0'
0)
0!
1#
1%
#35
0#
0%
#40
1'
1*
1"
1#
1%
#45
0#
0%
#50
0(
0*
0"
1)
1!
1#
1%
#55
0#
0%
#60
1(
0'
0)
0!
1#
1%
#65
0#
0%
#70
1'
1*
1"
1#
1%
#75
0#
0%
#80
0(
1)
1!
0*
0"
1#
1%
