implementation-of-state-diagram/5_50.v
//Jason Hatfield #29163434
// CSE 241 HW10 problem 5.50 verilog implementation of state diagram

module p5_50(y_out, x, clk, reset);

   input x, clk, reset;
   output y_out;
   reg [1:0] state;
   parameter s0 = 2'b00, s1 = 2'b01, s2 = 2'b10, s3 = 2'b11;

   always @(posedge clk, negedge reset)

	if(~reset) state <= s0;
	else   case(state)

		s0: if(x) state <= s1;
	 	s1: if(x) state <= s2;
		s2: if(x) state <= s3;
		s3: if(x) state <= s0;
	      
    	       endcase

   assign y_out = (state == s2) || (state == s3);
 

endmodule

hw10/5_50_tb.v
//Jason Hatfield #29163434
//CSE241 HW 10 problem 5_50 test bench

module t_p5_50;

   reg x, clk, reset;
   wire y;

   p5_50 c1(y, x, clk, reset);

   initial #200 $finish;

   initial 
	begin
	  clk = 0;
	  repeat(40) #5 clk = !clk;
	end
  
   initial 
	begin
	   reset = 0;
	   x = 0;
	   #5 reset = 1;
	   #5 x = 1;
	   #180 x = 0;
	end

   initial 
	begin
	   $monitor("T = %g, reset = %b, y = %b, x = %b", $time, reset, y, x);
	   $dumpfile("5_50_wv.vcd");
	   $dumpvars;
	end
endmodule

implementation-of-state-diagram/5_50_wv.vcd
$date
	Tue Dec  3 14:37:51 2013
$end
$version
	Icarus Verilog
$end
$timescale
	1s
$end
$scope module t_p5_50 $end
$var wire 1 ! y $end
$var reg 1 " clk $end
$var reg 1 # reset $end
$var reg 1 $ x $end
$scope module c1 $end
$var wire 1 % clk $end
$var wire 1 & reset $end
$var wire 1 ' x $end
$var wire 1 ! y_out $end
$var reg 2 ( state [1:0] $end
$upscope $end
$upscope $end
$enddefinitions $end
#0
$dumpvars
b0 (
0'
0&
0%
0$
0#
0"
0!
$end
#5
1#
1&
1"
1%
#10
1$
1'
0"
0%
#15
b1 (
1"
1%
#20
0"
0%
#25
1!
b10 (
1"
1%
#30
0"
0%
#35
b11 (
1"
1%
#40
0"
0%
#45
0!
b0 (
1"
1%
#50
0"
0%
#55
b1 (
1"
1%
#60
0"
0%
#65
1!
b10 (
1"
1%
#70
0"
0%
#75
b11 (
1"
1%
#80
0"
0%
#85
0!
b0 (
1"
1%
#90
0"
0%
#95
b1 (
1"
1%
#100
0"
0%
#105
1!
b10 (
1"
1%
#110
0"
0%
#115
b11 (
1"
1%
#120
0"
0%
#125
0!
b0 (
1"
1%
#130
0"
0%
#135
b1 (
1"
1%
#140
0"
0%
#145
1!
b10 (
1"
1%
#150
0"
0%
#155
b11 (
1"
1%
#160
0"
0%
#165
0!
b0 (
1"
1%
#170
0"
0%
#175
b1 (
1"
1%
#180
0"
0%
#185
1!
b10 (
1"
1%
#190
0"
0%
0$
0'
