Logic-assignment/5_41.v
// Jason Hatfield - #29163434
// HW9 - Problem 5.41 

module circuit_5_41(y_out, x, clk, reset);

   output reg y_out;

   input x, clk, reset;

   reg [2:0] state, nextstate;

   parameter s0 = 3'b000, s1 = 3'b001, s2 = 3'b010, s3 = 3'b011, s4 = 3'b100;

   always @(posedge clk, negedge reset)
	
	if(reset == 0)
	   state <= s0;

	else 
	   state <= nextstate;

   always @(state, x)

	begin

	   y_out = 0;
	   nextstate = s0;

	   case(state)

		s0:  if(x)

			begin

			   nextstate = s4;
			   y_out = 1;

			end

		     else

			begin

			   nextstate = s3;
			   y_out = 0;

			end

		s1:  if(x)

			begin

			   nextstate = s4;
			   y_out = 1;

			end

		     else

			begin

			   nextstate = s1;
			   y_out = 0;

			end

		s2:  if(x)

			begin

			   nextstate = s0;
			   y_out = 1;

			end

		     else

			begin

			   nextstate = s2;
			   y_out = 0;

			end

		s3:  if(x)

			begin

			   nextstate = s2;
			   y_out = 1;

			end

		     else

			begin

			   nextstate = s1;
			   y_out = 0;

			end

		s4:  if(x)

			begin

			   nextstate = s3;
			   y_out = 0;

			end

		     else

			begin

			   nextstate = s2;
			   y_out = 0;

			end

		default: nextstate = 3'bxxx;

	   endcase
	end
endmodule

Logic-assignment/5_41_tb.v
// Jason Hatfield - #29163434
//  HW9 5.41 test bench

module circuit_5_41_tb;

   wire y_out;

   reg x, clk, reset;

   circuit_5_41 c1(y_out, x, clk, reset);

   initial #200 $finish;

   initial

	begin
	   clk = 0;

	   repeat(40) #5 clk = ~clk;
	end

   initial

	begin
	   // Initialize x and reset

	   x = 0;
	   
	   #2 reset = 1;
	   #3 reset = 0;
	   #4 reset = 1;

	   // Initialize counting	
	   #10 x = 1;
	   // Reverse Count
	   #100 x = 0;
	   // Reverse
	   #150 x = 1;
	end

   initial
	begin
	   $monitor("time = %g, reset = %b, x = %b, y_out = %b", $time, reset, x, y_out);
	   $dumpfile("5_41_wv.vcd");	
	   $dumpvars;
	end
endmodule

hw9/5_41_wv.vcd
$date
	Sun Dec  1 15:24:58 2013
$end
$version
	Icarus Verilog
$end
$timescale
	1s
$end
$scope module circuit_5_41_tb $end
$var wire 1 ! y_out $end
$var reg 1 " clk $end
$var reg 1 # reset $end
$var reg 1 $ x $end
$scope module c1 $end
$var wire 1 % clk $end
$var wire 1 & reset $end
$var wire 1 ' x $end
$var reg 3 ( nextstate [2:0] $end
$var reg 3 ) state [2:0] $end
$var reg 1 * y_out $end
$upscope $end
$upscope $end
$enddefinitions $end
#0
$dumpvars
0*
bx )
bx (
0'
x&
0%
0$
x#
0"
0!
$end
#2
1#
1&
#5
b11 (
b0 )
0#
0&
1"
1%
#9
1#
1&
#10
0"
0%
#15
b1 (
b11 )
1"
1%
#19
1*
1!
b10 (
1$
1'
#20
0"
0%
#25
b0 (
1*
1!
b10 )
1"
1%
#30
0"
0%
#35
b100 (
1*
1!
b0 )
1"
1%
#40
0"
0%
#45
b11 (
0*
0!
b100 )
1"
1%
#50
0"
0%
#55
1*
1!
b10 (
b11 )
1"
1%
#60
0"
0%
#65
b0 (
1*
1!
b10 )
1"
1%
#70
0"
0%
#75
b100 (
1*
1!
b0 )
1"
1%
#80
0"
0%
#85
b11 (
0*
0!
b100 )
1"
1%
#90
0"
0%
#95
1*
1!
b10 (
b11 )
1"
1%
#100
0"
0%
#105
b0 (
1*
1!
b10 )
1"
1%
#110
0"
0%
#115
b100 (
1*
1!
b0 )
1"
1%
#119
b11 (
0*
0!
0$
0'
#120
0"
0%
#125
b1 (
b11 )
1"
1%
#130
0"
0%
#135
b1 (
b1 )
1"
1%
